dm_nevis
